Workbook

Sheet 表紙
B2: 御 見 積 書
C4: 見積番号 | D4: FSW-2026-1595-001
C5: 発行日 | D5: 2026年4月1日
C6: 有効期限 | D6: 発行日より30日間有効
B8: 株式会社Skrum 御中
B9: 下記の通り御見積申し上げます。
B11: 件名： AiBoシステム開発
B13: 概算見積額（税別） | D13: ※シナリオにより異なります — 詳細は「概算見積」シートをご参照ください
B14: S1: ¥2,600,000 ～ S4: ¥11,500,000（概算、±20%変動あり）
C16: シナリオ | D16: 説明 | E16: 概算額（税別） | F16: GT責任
B17: S1 | C17: S1 | D17: Skrum:AI+BE, Fabbi:FE | E17: ¥2,600,000 | F17: Skrum
B18: S2 | C18: S2 | D18: Skrum:AI, Fabbi:BE+FE ★ | E18: ¥7,900,000 | F18: Fabbi
B19: S3 | C19: S3 | D19: Fabbi:全+HITL 80% ★★ | E19: ¥9,800,000 | F19: Fabbi
B20: S4 | C20: S4 | D20: Fabbi:全 90%純AI | E20: ¥11,500,000 | F20: Fabbi
B22: 発行元
C23: 会社名 | D23: Fabbi Software JSC
C24: 部署 | D24: ソフトウェア開発部
C25: 住所 | D25: Ho Chi Minh City, Vietnam
C26: Email | D26: info@fabbi.com.vn
C27: Web | D27: https://fabbi.com.vn

Sheet 概算見積
A1: 概算見積書 — シナリオ比較
B2: 【Skrum様】AiBoシステム
A3: 工程 | B3: S1（2.6MM） | C3: S2（7.9MM） | D3: S3（9.8MM） | E3: S4（11.5MM） | F3: 備考
A4: 担当説明 | B4: Skrum:AI+BE Fabbi:FE | C4: Skrum:AI Fabbi:BE+FE | D4: Fabbi:全+HITL 80% | E4: Fabbi:全 90%純AI | F4: AIパイプライン責任
A5: GT責任者 | B5: Skrum | C5: Fabbi | D5: Fabbi | E5: Fabbi | F5: GT=グラウンドトゥルース
A7: 要件定義・基本設計（10%） | B7: 0.3 | C7: 0.8 | D7: 1 | E7: 1.2 | F7: スコープ確定・画面設計
A8: 詳細設計（15%） | B8: 0.4 | C8: 1.2 | D8: 1.5 | E8: 1.7 | F8: API設計・DB設計
A9: 製造（AI+BE+FE）（40%） | B9: 1 | C9: 3.2 | D9: 3.9 | E9: 4.6 | F9: 最大工数フェーズ
A10: 単体試験（15%） | B10: 0.4 | C10: 1.2 | D10: 1.5 | E10: 1.7 | F10: UT・機能確認
A11: 結合試験（10%） | B11: 0.3 | C11: 0.8 | D11: 1 | E11: 1.2 | F11: IT・シナリオテスト
A12: PM / BrSE（10%） | B12: 0.3 | C12: 0.8 | D12: 1 | E12: 1.2 | F12: 進捗管理・橋渡し
A13: 合計（概算・税別） | B13: 2.6 | C13: 7.9 | D13: 9.8 | E13: 11.5 | F13: ※±20%変動あり
B15: S1 | C15: S2 | D15: S3 | E15: S4 | F15: 単価前提
A16: 概算金額（税別） | B16: 3120000 | C16: 9480000 | D16: 11760000 | E16: 13800000 | F16: @¥1,200,000/人月
A18: 推奨 | C18: ★ 推奨 | D18: ★★ 最推奨 | F18: ★★=Fabbi全担当+HITL品質保証
A20: シナリオ説明
A21: S1 | B21: Skrum側でAI・BEを担当。Fabbi担当はFEのみ。最小コストだが品質GTはSkrum依存。
A22: S2 | B22: Skrum担当はAIパイプラインのみ。Fabbi担当はBE+FE。GT提供はSkrum。★推奨：役割明確
A23: S3 | B23: Fabbi全担当（AI+BE+FE）。HITL（人間確認ループ）80%で品質保証。★★最推奨
A24: S4 | B24: Fabbi全担当。90%純AI化（HITL最小）。高速だが精度リスクあり。追加QA必要。
A25: GT | B25: GT（Ground Truth）= 提案書・見積書・請求書の模範文書。S1-2はSkrum提供、S3-4はFabbi調達。
A27: S3推奨理由 | B27: 主要な要因 | C27: S3が最適な理由
A28: 品質保証 | B28: HITL 80%でSkrum様の精度要望に対応 | C28: AI出力の品質リスク低減
A29: 責任明確 | B29: Fabbi単独でGT提供可能 | C29: Skrum様のGT調達負荷軽減
A30: コストバランス | B30: 9.8MMは補助金枠内対応可能 | C30: ものづくり補助金活用しやすい
A31: 技術実績 | B31: FabbiのAIプラットフォーム経験活用 | C31: 類似案件（Domus等）の実績反映

Sheet AI仕様書
A1: AI仕様書 — AiBoシステム開発
A3: 1. LLMプロバイダ選定
A4: 項目 | B4: 推奨 | C4: 代替案 | D4: 備考
A5: プロバイダ | B5: OpenAI GPT-4o | C5: Anthropic Claude 3.5 Sonnet | D5: コストパフォーマンス重視
A6: 利用モデル | B6: gpt-4o-2024-05-13 | C6: claude-3-5-sonnet-20241022 | D6: 日本語対応可
A7: 月間推定コスト | B7: ¥50,000〜¥150,000 | C7: ¥80,000〜¥200,000 | D7: 利用量による変動
A9: 2. AI機能別仕様
A10: 機能 | B10: 技術 | C10: 精度目標 | D10: HITL確認率
A11: AIコンテンツ抽出 | B11: OCR + LLM | C11: 95%以上 | D11: 100%（必須確認）
A12: 提案書作成 | B12: GPT-4o + Template | C12: 90%以上 | D12: 80%
A13: 見積書作成 | B13: GPT-4o + Template | C13: 95%以上（計算） | D13: 80%
A14: 請求書作成 | B14: GPT-4o + Template | C14: 100%（形式） | D14: 100%（法務確認必須）
A15: 競合分析 | B15: Web検索 + LLM要約 | C15: 70%以上 | D15: 100%（情報源確認）
A17: 3. 前提条件
A18: 項目 | B18: 条件
A19: GT（模範文書） | B19: Skrum様よりご提供：各種類5〜10件
A20: GT納期 | B20: 契約後30日以内
A21: POC期間 | B21: 基本設計完了後2週間 | C21: 精度検証用
A23: 4. リスク対策
A24: リスク | B24: 対策 | C24: 担当
A25: LLMサービス停止 | B25: 複数プロバイダ契約可能 | C25: Fabbi
A26: 精度不足 | B26: HITLループで改善 | C26: Fabbi + Skrum様
A27: コスト超過 | B27: 月間上限設定 + アラート | C27: Fabbi

Sheet 詳細見積
A1: 詳細見積書（WBSレベル）— AiBoシステム開発
A3: WBS ID | B3: カテゴリ | C3: 機能名 | D3: AI (MD) | E3: BE (MD) | F3: FE (MD) | G3: QA (MD) | H3: 合計 (MD) | I3: 人月 | J3: 備考
A4: AIBO-001 | B4: ダッシュボード | C4: ダッシュボード | D4: 0 | E4: 0.5 | F4: 1 | G4: 2 | H4: =SUM(D4:G4) | I4: =H4/20
A5: 小計 ダッシュボード | D5: =SUM(D4) | E5: =SUM(E4) | F5: =SUM(F4) | G5: =SUM(G4) | H5: =SUM(H4) | I5: =H5/20
A6: AIBO-002 | B6: ファイル管理 | C6: ファイルアップロード | D6: 0 | E6: 0.5 | F6: 0.5 | G6: 0.4 | H6: =SUM(D6:G6) | I6: =H6/20
A7: 小計 ファイル管理 | D7: =SUM(D6) | E7: =SUM(E6) | F7: =SUM(F6) | G7: =SUM(G6) | H7: =SUM(H6) | I7: =H7/20
A8: AIBO-003 | B8: AI文書生成 | C8: AIコンテンツ抽出 | D8: 12 | E8: 2 | F8: 1 | G8: 8 | H8: =SUM(D8:G8) | I8: =H8/20 | J8: ⚠️ AI重要機能
A9: 小計 AI文書生成 | D9: =SUM(D8) | E9: =SUM(E8) | F9: =SUM(F8) | G9: =SUM(G8) | H9: =SUM(H8) | I9: =H9/20
A10: AIBO-004 | B10: ファイル管理 | C10: ファイル一覧・並替 | D10: 0 | E10: 0.5 | F10: 1.5 | G10: 1 | H10: =SUM(D10:G10) | I10: =H10/20
A11: AIBO-005 | B11: ファイル管理 | C11: ファイル削除 | D11: 0 | E11: 0.15 | F11: 0.1 | G11: 0.1 | H11: =SUM(D11:G11) | I11: =H11/20
A12: AIBO-006 | B12: ファイル管理 | C12: ファイルダウンロード | D12: 0 | E12: 0.5 | F12: 0.5 | G12: 0.5 | H12: =SUM(D12:G12) | I12: =H12/20
A13: 小計 ファイル管理 | D13: =SUM(D10,D11,D12) | E13: =SUM(E10,E11,E12) | F13: =SUM(F10,F11,F12) | G13: =SUM(G10,G11,G12) | H13: =SUM(H10,H11,H12) | I13: =H13/20
A14: AIBO-007 | B14: AI文書生成 | C14: 提案書作成 | D14: 7 | E14: 2 | F14: 1 | G14: 3 | H14: =SUM(D14:G14) | I14: =H14/20 | J14: ⚠️ AI重要機能
A15: AIBO-008 | B15: AI文書生成 | C15: 見積書作成 | D15: 3 | E15: 1 | F15: 1 | G15: 3 | H15: =SUM(D15:G15) | I15: =H15/20
A16: AIBO-009 | B16: AI文書生成 | C16: 請求書作成 | D16: 3 | E16: 1 | F16: 1 | G16: 3 | H16: =SUM(D16:G16) | I16: =H16/20
A17: AIBO-010 | B17: AI文書生成 | C17: 競合分析 | D17: 3.5 | E17: 0.5 | F17: 1 | G17: 3 | H17: =SUM(D17:G17) | I17: =H17/20 | J17: ⚠️ AI重要機能
A18: 小計 AI文書生成 | D18: =SUM(D14,D15,D16,D17) | E18: =SUM(E14,E15,E16,E17) | F18: =SUM(F14,F15,F16,F17) | G18: =SUM(G14,G15,G16,G17) | H18: =SUM(H14,H15,H16,H17) | I18: =H18/20
A19: AIBO-011 | B19: AI設定 | C19: AIテンプレート設定 | D19: 6 | E19: 2 | F19: 2 | G19: 6 | H19: =SUM(D19:G19) | I19: =H19/20 | J19: ⚠️ AI重要機能
A20: AIBO-012 | B20: AI設定 | C20: マーケットプレイス | D20: 0 | E20: 2.5 | F20: 2.5 | G20: 3 | H20: =SUM(D20:G20) | I20: =H20/20
A21: 小計 AI設定 | D21: =SUM(D19,D20) | E21: =SUM(E19,E20) | F21: =SUM(F19,F20) | G21: =SUM(G19,G20) | H21: =SUM(H19,H20) | I21: =H21/20
A22: AIBO-013 | B22: 設定 | C22: ユーザ情報 | D22: 0 | E22: 0.5 | F22: 1 | G22: 0.5 | H22: =SUM(D22:G22) | I22: =H22/20
A23: AIBO-014 | B23: 設定 | C23: 料金プラン | D23: 0 | E23: 2 | F23: 2 | G23: 1.5 | H23: =SUM(D23:G23) | I23: =H23/20
A24: AIBO-015 | B24: 設定 | C24: 通知設定 | D24: 0 | E24: 0.25 | F24: 0.75 | G24: 0.25 | H24: =SUM(D24:G24) | I24: =H24/20
A25: AIBO-016 | B25: 設定 | C25: パスワード変更 | D25: 0 | E25: 0.15 | F25: 0.1 | G25: 0.1 | H25: =SUM(D25:G25) | I25: =H25/20
A26: 小計 設定 | D26: =SUM(D22,D23,D24,D25) | E26: =SUM(E22,E23,E24,E25) | F26: =SUM(F22,F23,F24,F25) | G26: =SUM(G22,G23,G24,G25) | H26: =SUM(H22,H23,H24,H25) | I26: =H26/20
A27: AIBO-017 | B27: お問合せ | C27: お問合せフォーム | D27: 0 | E27: 0.15 | F27: 0.1 | G27: 0.1 | H27: =SUM(D27:G27) | I27: =H27/20
A28: 小計 お問合せ | D28: =SUM(D27) | E28: =SUM(E27) | F28: =SUM(F27) | G28: =SUM(G27) | H28: =SUM(H27) | I28: =H28/20
A29: AIBO-018 | B29: 管理:認証 | C29: ログイン・ログアウト | D29: 0 | E29: 0.3 | F29: 0.2 | G29: 0.25 | H29: =SUM(D29:G29) | I29: =H29/20
A30: 小計 管理:認証 | D30: =SUM(D29) | E30: =SUM(E29) | F30: =SUM(F29) | G30: =SUM(G29) | H30: =SUM(H29) | I30: =H30/20
A31: AIBO-019 | B31: 管理:テナント | C31: テナント一覧・検索 | D31: 0 | E31: 0.2 | F31: 0.3 | G31: 0.2 | H31: =SUM(D31:G31) | I31: =H31/20
A32: AIBO-020 | B32: 管理:テナント | C32: テナント作成 | D32: 0 | E32: 1 | F32: 0.5 | G32: 0.8 | H32: =SUM(D32:G32) | I32: =H32/20
A33: AIBO-021 | B33: 管理:テナント | C33: テナント編集 | D33: 0 | E33: 0.4 | F33: 0.35 | G33: 0.4 | H33: =SUM(D33:G33) | I33: =H33/20
A34: AIBO-022 | B34: 管理:テナント | C34: テナント停止・削除 | D34: 0 | E34: 0.3 | F34: 0.2 | G34: 0.2 | H34: =SUM(D34:G34) | I34: =H34/20
A35: 小計 管理:テナント | D35: =SUM(D31,D32,D33,D34) | E35: =SUM(E31,E32,E33,E34) | F35: =SUM(F31,F32,F33,F34) | G35: =SUM(G31,G32,G33,G34) | H35: =SUM(H31,H32,H33,H34) | I35: =H35/20
A36: AIBO-023 | B36: 管理:プラン | C36: プラン一覧 | D36: 0 | E36: 0.05 | F36: 0.2 | G36: 0.1 | H36: =SUM(D36:G36) | I36: =H36/20
A37: AIBO-024 | B37: 管理:プラン | C37: プラン編集 | D37: 0 | E37: 0.3 | F37: 0.2 | G37: 0.2 | H37: =SUM(D37:G37) | I37: =H37/20
A38: 小計 管理:プラン | D38: =SUM(D36,D37) | E38: =SUM(E36,E37) | F38: =SUM(F36,F37) | G38: =SUM(G36,G37) | H38: =SUM(H36,H37) | I38: =H38/20
A40: 合計 | D40: =SUM(D4,D10,D11,D12,D14,D15,D16,D17,D19,D20,D22,D23,D24,D25,D27,D29,D31,D32,D33,D34,D36,D37) | E40: =SUM(E4,E10,E11,E12,E14,E15,E16,E17,E19,E20,E22,E23,E24,E25,E27,E29,E31,E32,E33,E34,E36,E37) | F40: =SUM(F4,F10,F11,F12,F14,F15,F16,F17,F19,F20,F22,F23,F24,F25,F27,F29,F31,F32,F33,F34,F36,F37) | G40: =SUM(G4,G10,G11,G12,G14,G15,G16,G17,G19,G20,G22,G23,G24,G25,G27,G29,G31,G32,G33,G34,G36,G37) | H40: =SUM(D40:G40) | I40: =H40/20
A42: 凡例: | C42: AI重要機能（AI工数 > 0） | E42: BE重点機能 | G42: 標準機能

Sheet 前提条件
A1: 前提条件・制約条件 — AiBoシステム開発
A3: 1. 見積の範囲（スコープ）
B4: ユーザアプリ（Web） | C4: 17機能（ダッシュボード・ファイル管理・AI文書生成・AI設定・設定・お問合せ）
B5: 管理アプリ（Web） | C5: 7機能（認証・テナント管理・プラン管理）
B6: 合計 | C6: 24機能、詳細は「詳細見積」シート参照
A8: 2. 含まれないもの（対象外）
B9: × 17画面仕様 | C9: ポートフォリオ・コミュニティ機能（別途見積対応）
B10: × AI APIコスト | C10: OpenAI / Claude等のランタイム費用（実費精算）
B11: × インフラ構築 | C11: サーバ構築・ホスティング費用（別途）
B12: × 運用保守 | C12: 本番稼働後の保守対応（別途契約）
B13: × モバイルアプリ | C13: iOS / Android ネイティブ対応
B14: × セキュリティ監査 | C14: ISMS・ペネトレーションテスト等
A16: 3. 前提条件
B17: ○ 要件確定 | C17: 見積承認後30日以内に要件を確定すること
B18: ○ Figmaデザイン | C18: 開発開始前に確定版デザインを提供いただくこと
B19: ○ テスト環境 | C19: テスト環境はFabbi側で構築・管理
B20: ○ LLMプロバイダ | C20: AI LLMの選定・契約：S1=Skrum手配、S2-S4=Fabbi手配
B21: ○ GTサンプル | C21: 提案書・見積書・請求書の模範文書（GT）を客先よりご提供いただくこと
A23: 4. 確認事項（未回答）
B24: Q1 | C24: AIパイプラインの責任分担（Skrum担当 vs Fabbi担当）の確定
B25: Q2 | C25: AI出力の受入基準（GT定義・品質レベル・人間確認ループ割合）
B26: Q3 | C26: 17画面仕様（ポートフォリオ・コミュニティ）のスコープ包含可否
B27: Q4 | C27: 競合分析機能のデータソース（外部API・手動入力・クロール等）
B28: Q5 | C28: インボイス制度対応の要否（適格請求書発行事業者登録番号等）
A30: 5. 制約条件
B31: ！ 見積精度 | C31: 概算見積のため±20%の変動あり。確定見積は要件定義完了後
B32: ！ 追加要件 | C32: スコープ外の追加要件は別途お見積り
B33: ！ スケジュール | C33: 着手日確定後に詳細スケジュールを提示（「スケジュール」シート参照）
B34: ！ リソース | C34: S3前提：2〜3名チーム（FE×1 + BE/AI×1 + QA×0.5 + PM×0.5）
A36: 4. 前提と仮定（確定事項）
B37: 項目 | C37: 内容 | D37: ステータス
B38: AIプロバイダ | C38: OpenAI GPT-4o（推奨）、変更可 | D38: 確定後契約
B39: GT（模範文書） | C39: Skrum様より契約後30日以内にご提供 | D39: 必須
B40: AI精度目標 | C40: 文書生成90%以上・コンテンツ抽出95%以上 | D40: POC検証後確定
B41: 競合分析データ | C41: 手動入力＋公開情報の検索 | D41: 仕様確定時
B42: インボイス制度 | C42: 要対応（適格請求書番号項目実装） | D42: 基本設計反映
B43: 17画面仕様 | C43: 本見積対象外（別途見積） | D43: スコープ外
B44: ものづくり補助金 | C44: 本見積は補助金申請書類として使用可能 | D44: 対応済

Sheet カテゴリ別集計
A1: カテゴリ別集計
A3: カテゴリ | B3: 機能数 | C3: AI (MD) | D3: BE (MD) | E3: FE (MD) | F3: QA (MD) | G3: 合計 (MD) | H3: 人月 | I3: 割合(%)
A4: ダッシュボード | B4: 1 | D4: 0.5 | E4: 1 | F4: 2 | G4: 3.5 | H4: 0.17 | I4: 100%
A5: ファイル管理 | B5: 4 | D5: 1.65 | E5: 2.6 | F5: 2 | G5: 6.25 | H5: 0.31 | I5: 64%
A6: AI文書生成 | B6: 5 | C6: 28.5 | D6: 6.5 | E6: 5 | F6: 20 | G6: 60 | H6: 3 | I6: 86%
A7: AI設定 | B7: 2 | D7: 0.65 | E7: 0.6 | F7: 0.6 | G7: 1.85 | H7: 0.09 | I7: 3%
A8: 設定 | B8: 4 | C8: 13 | D8: 4 | E8: 3 | F8: 9 | G8: 29 | H8: 1.45 | I8: 29%
A9: お問合せ | B9: 1 | C9: 3.5 | D9: 0.5 | E9: 1 | F9: 3 | G9: 8 | H9: 0.4 | I9: 7%
A10: 管理:認証 | B10: 1 | I10: 0%
A11: 管理:テナント | B11: =COUNTIF(詳細見積!$B$4:$B$40,"管理:テナント") | C11: =SUMIF(詳細見積!$B$4:$B$40,"管理:テナント",詳細見積!$D$4:$D$40) | D11: =SUMIF(詳細見積!$B$4:$B$40,"管理:テナント",詳細見積!$E$4:$E$40) | E11: =SUMIF(詳細見積!$B$4:$B$40,"管理:テナント",詳細見積!$F$4:$F$40) | F11: =SUMIF(詳細見積!$B$4:$B$40,"管理:テナント",詳細見積!$G$4:$G$40) | G11: =C11+D11+E11+F11 | H11: =G11/20 | I11: =G11/G14
A12: 管理:プラン | B12: =COUNTIF(詳細見積!$B$4:$B$40,"管理:プラン") | C12: =SUMIF(詳細見積!$B$4:$B$40,"管理:プラン",詳細見積!$D$4:$D$40) | D12: =SUMIF(詳細見積!$B$4:$B$40,"管理:プラン",詳細見積!$E$4:$E$40) | E12: =SUMIF(詳細見積!$B$4:$B$40,"管理:プラン",詳細見積!$F$4:$F$40) | F12: =SUMIF(詳細見積!$B$4:$B$40,"管理:プラン",詳細見積!$G$4:$G$40) | G12: =C12+D12+E12+F12 | H12: =G12/20 | I12: =G12/G14
A14: 合計 | B14: =SUM(B4:B12) | C14: =SUM(C4:C12) | D14: =SUM(D4:D12) | E14: =SUM(E4:E12) | F14: =SUM(F4:F12) | G14: =SUM(G4:G12) | H14: =G14/20 | I14: 100.0%
A16: ※ AI文書生成・AI設定 の合計工数が全体の約60-70%を占める（AIパイプライン複雑度による）

Sheet 支払条件
A1: 支払条件 — AiBoシステム開発
A3: 【Skrum様】支払スケジュール
A4: 回 | B4: タイミング | C4: 支払割合 | D4: 金額（税別） | E4: 条件
A5: 1回目 | B5: 契約時 | C5: 30% | D5: ¥2,940,000 | E5: 契約締後5営業日以内
A6: 2回目 | B6: MS-04：全機能実装完了 | C6: 40% | D6: ¥3,920,000 | E6: コードFIX完了確認後5営業日以内
A7: 3回目 | B7: MS-07：受入テスト完了・納品 | C7: 30% | D7: ¥2,940,000 | E7: UAT完了・納品物引渡後5営業日以内
A9: 合計 | C9: 100% | D9: ¥9,800,000
A11: 【Skrum様】提供事項
A12: 項目 | B12: 内容 | C12: 期限
A13: GT（模範文書） | B13: 提案書・見積書・請求書 各5〜10件 | C13: 契約後30日以内
A14: Figmaデザイン | B14: 確定版画面デザイン | C14: 開発開始1週間前
A15: テストデータ | B15: 各機能のテスト用データ | C15: 結合試験開始時
A16: ※ ものづくり補助金申請用として本見積をご利用いただけます。 | B16: UAT実施環境（Web） | C16: UAT開始時
A18: ※ 支払は銀行振込。振込手数料はSkrum様負担。
A19: ※ ものづくり補助金申請用として本見積をご利用いただけます。

Sheet スケジュール
A1: プロジェクトスケジュール — S3シナリオ（推奨：9.8MM、約5ヶ月）
A2: プロジェクトスケジュール — Skrum様 AiBo (S3)
A3: フェーズ | B3: 開始 | C3: 終了 | D3: 期間 | E3: 備考
A4: 要件定義 | B4: M1 W1 | C4: M1 W3 | D4: 3週間 | E4: ヒアリング・スコープ確定・要件書作成
A5: 基本設計 | B5: M1 W3 | C5: M2 W2 | D5: 3週間 | E5: アーキテクチャ・画面設計・API設計
A6: 詳細設計 | B6: M2 W2 | C6: M3 W1 | D6: 3週間 | E6: DB設計・詳細仕様・インターフェース定義
A7: 製造（Sprint 1） | B7: M3 W1 | C7: M3 W3 | D7: 2週間 | E7: ダッシュボード・認証・ファイル管理基盤
A8: 製造（Sprint 2） | B8: M3 W3 | C8: M4 W2 | D8: 2週間 | E8: AI文書生成コア（提案書・見積書）
A9: 製造（Sprint 3） | B9: M4 W2 | C9: M5 W1 | D9: 3週間 | E9: 競合分析・AIテンプレート・マーケット
A10: 製造（Sprint 4） | B10: M5 W1 | C10: M5 W2 | D10: 1週間 | E10: 管理機能・設定・バグ修正
A11: 単体試験 | B11: M4 W1 | C11: M5 W3 | D11: 並行 | E11: 開発と並行実施（自動テスト + レビュー）
A12: 結合試験 | B12: M5 W3 | C12: M6 W2 | D12: 3週間 | E12: シナリオテスト・APIテスト・負荷テスト
A13: 受入テスト支援 | B13: M6 W2 | C13: M6 W4 | D13: 2週間 | E13: UAT支援・不具合対応・リリース準備
A15: 主要マイルストーン
A16: MS-01 | B16: M1 W4 | C16: 要件定義完了・スコープFIX
A17: MS-02 | B17: M2 W4 | C17: 基本設計完了・画面FIX
A18: MS-03 | B18: M3 W4 | C18: 詳細設計完了・DB FIX
A19: MS-04 | B19: M5 W2 | C19: 全機能実装完了（コードFIX）
A20: MS-05 | B20: M5 W4 | C20: 単体試験完了
A21: MS-06 | B21: M6 W3 | C21: 結合試験完了・本番候補リリース
A22: MS-07 | B22: M6 W4 | C22: 受入テスト完了・納品 | E22: ★最終マイルストーン
A24: ※ M = 着手月（プロジェクト開始月を M1 とする相対表記）。W = 週。
A25: ※ S3シナリオ前提：2〜3名チーム（FE×1 + BE/AI×1 + QA×0.5 + PM×0.5）
A26: ※ 製造フェーズはアジャイル（2週スプリント）で進行。スプリントごとにデモを実施。
A27: ※ 着手日確定後、Mを実際の暦日付に変換した詳細ガントチャートを提出可能。
A28: ※ チーム構成：平均1.7名（FE×0.6 + BE/AI×0.8 + QA×0.3 + PM×0.5）
A29: ※ ピーク時：製造フェーズで最大2.5名（FE×1 + BE/AI×1 + QA×0.5）
