Workbook

Sheet 概算見積
A1: 概算見積書 — シナリオ比較
B2: 【Skrum様】AiBoシステム
A3: 工程 | B3: S1 | C3: S2 | D3: S3 | E3: S4 | F3: 備考
A4: 担当説明 | B4: Skrum:AI+BE Fabbi:FE | C4: Skrum:AI Fabbi:BE+FE | D4: Fabbi:全 80%純AI | E4: Fabbi:全 90%純AI | F4: AIパイプライン責任
A5: GT責任者 | B5: Skrum | C5: Skrum | D5: Fabbi | E5: Fabbi | F5: GT=グラウンドトゥルース
A7: 要件定義・基本設計 | B7: 0 | C7: 0 | D7: 0 | E7: 0 | F7: スコープ確定・画面設計
A8: 詳細設計 | B8: 0 | C8: 0 | D8: 0 | E8: 0 | F8: API設計・DB設計
A9: 製造 | B9: =SUM(詳細見積!G4:G27) / 20 -> 1.93 | C9: =SUM(詳細見積!F4:G27)/20 -> 3.835 | D9: =C9+SUM(詳細見積!D4:D27)/20 -> 5.385 | E9: =C9+SUM(詳細見積!E4:E27)/20 -> 6.635 | F9: 最大工数フェーズ
A10: 単体試験 | B10: =SUM(詳細見積!H4:H27)/20 -> 0.965 | C10: =SUM(詳細見積!I4:I27)/20 -> 1.727 | D10: =SUM(詳細見積!J4:J27)/20 -> 2.657 | E10: =SUM(詳細見積!K4:K27)/20 -> 3.407 | F10: UT・機能確認
A11: 結合試験 | B11: 0.5 | C11: 0.3 | D11: 0.3 | E11: 0.3 | F11: IT・シナリオテスト
A12: PM / BrSE（10%） | B12: =10%*SUM(B7:B11) -> 0.3395 | C12: =10%*SUM(C7:C11) -> 0.5862 | D12: =10%*SUM(D7:D11) -> 0.8342 | E12: =10%*SUM(E7:E11) -> 1.0342 | F12: 進捗管理・橋渡し
A13: 合計（概算・税別） | B13: =SUM(B7:B12) -> 3.7345 | C13: =SUM(C7:C12) -> 6.4482 | D13: =SUM(D7:D12) -> 9.1762 | E13: =SUM(E7:E12) -> 11.3762 | F13: ※±20%変動あり
B15: S1 | C15: S2 | D15: S3 | E15: S4 | F15: 単価前提
A16: 概算金額（税別） | B16: =B13*$F$16 -> 1493800 | C16: =C13*$F$16 -> 2579280 | D16: =D13*$F$16 -> 3670480 | E16: =E13*$F$16 -> 4550480 | F16: 400000
A18: 推奨 | C18: ★ 推奨 | D18: ★★ 最推奨 | F18: ★★=Fabbi全担当+HITL品質保証
A20: シナリオ説明
A21: S1 | B21: Skrum側でAI・BEを担当。Fabbi担当はFEのみ。最小コストだが品質GTはSkrum依存。
A22: S2 | B22: Skrum担当はAIパイプラインのみ。Fabbi担当はBE+FE。GT提供はSkrum。★推奨：役割明確
A23: S3 | B23: Fabbi全担当（AI+BE+FE）。HITL（人間確認ループ）80%で品質保証。★★最推奨
A24: S4 | B24: Fabbi全担当。90%純AI化（HITL最小）。高速だが精度リスクあり。追加QA必要。
A25: GT | B25: GT（Ground Truth）= 提案書・見積書・請求書の模範文書。S1-2はSkrum提供、S3-4はFabbi調達。
A27: S3推奨理由 | B27: 主要な要因 | D27: S3が最適な理由
A28: 品質保証 | B28: HITL 80%でSkrum様の精度要望に対応 | D28: AI出力の品質リスク低減
A29: 責任明確 | B29: Fabbi単独でGT提供可能 | D29: Skrum様のGT調達負荷軽減

Sheet AI仕様書
A1: AI仕様書 — AiBoシステム開発
A3: 1. LLMプロバイダ選定
A4: 項目 | B4: 推奨 | C4: 代替案 | D4: 備考
A5: プロバイダ | B5: OpenAI GPT-4o | C5: Anthropic Claude 4.5 Sonnet | D5: コストパフォーマンス重視
A6: 利用モデル | B6: gpt-5o | C6: claude-4-5-sonnet | D6: 日本語対応可
A7: 月間推定コスト | B7: ¥50,000〜¥150,000 | C7: ¥80,000〜¥200,000 | D7: 利用量による変動
A9: 2. AI機能別仕様
A10: 項目 | B10: 推奨 | C10: 代替案 | D10: 備考
A11: AIコンテンツ抽出 | B11: OCR + LLM | C11: 95%以上 | D11: 100%（必須確認）
A12: 提案書作成 | B12: GPT-4o + Template | C12: 90%以上 | D12: 80%
A13: 見積書作成 | B13: GPT-4o + Template | C13: 95%以上（計算） | D13: 80%
A14: 請求書作成 | B14: GPT-4o + Template | C14: 100%（形式） | D14: 100%（法務確認必須）
A15: 競合分析 | B15: Web検索 + LLM要約 | C15: 70%以上 | D15: 100%（情報源確認）
A17: 3. 前提条件
A18: 項目 | B18: 項目
A19: GT（模範文書） | B19: Skrum様よりご提供：各種類5〜10件
A20: GT納期 | B20: 契約後30日以内
A21: POC期間 | B21: 基本設計完了後2週間 (精度検証用)
A23: 4. リスク対策
A24: リスク | B24: 対策 | C24: 担当
A25: LLMサービス停止 | B25: 複数プロバイダ契約可能 | C25: Fabbi
A26: 精度不足 | B26: HITLループで改善 | C26: Fabbi + Skrum様
A27: コスト超過 | B27: 月間上限設定 + アラート | C27: Fabbi

Sheet 前提条件
A1: 前提条件・制約条件 — AiBoシステム開発
A3: 1. 見積の範囲（スコープ）
B4: ユーザアプリ（Web） | C4: 17機能（ダッシュボード・ファイル管理・AI文書生成・AI設定・設定・お問合せ）
B5: 管理アプリ（Web） | C5: 7機能（認証・テナント管理・プラン管理）
B6: 合計 | C6: 24機能、詳細は「詳細見積」シート参照
A8: 2. 含まれないもの（対象外）
B9: × 17画面仕様 | C9: ポートフォリオ・コミュニティ機能（別途見積対応）
B10: × AI APIコスト | C10: OpenAI / Claude等のランタイム費用（実費精算）
B11: × インフラ構築 | C11: サーバ構築・ホスティング費用（別途）
B12: × 運用保守 | C12: 本番稼働後の保守対応（別途契約）
B13: × モバイルアプリ | C13: iOS / Android ネイティブ対応
B14: × セキュリティ監査 | C14: ISMS・ペネトレーションテスト等
A16: 3. 前提条件
B17: ○ 要件確定 | C17: 見積承認後30日以内に要件を確定すること
B18: ○ Figmaデザイン | C18: 開発開始前に確定版デザインを提供いただくこと
B19: ○ テスト環境 | C19: テスト環境はFabbi側で構築・管理
B20: ○ LLMプロバイダ | C20: AI LLMの選定・契約：S1=Skrum手配、S2-S4=Fabbi手配
B21: ○ GTサンプル | C21: 提案書・見積書・請求書の模範文書（GT）を客先よりご提供いただくこと
A23: 4. 確認事項（未回答）
B24: Q1 | C24: AIパイプラインの責任分担（Skrum担当 vs Fabbi担当）の確定
B25: Q2 | C25: AI出力の受入基準（GT定義・品質レベル・人間確認ループ割合）
B26: Q3 | C26: 17画面仕様（ポートフォリオ・コミュニティ）のスコープ包含可否
B27: Q4 | C27: 競合分析機能のデータソース（外部API・手動入力・クロール等）
B28: Q5 | C28: インボイス制度対応の要否（適格請求書発行事業者登録番号等）
A30: 5. 制約条件
B31: ！ 見積精度 | C31: 概算見積のため±20%の変動あり。確定見積は要件定義完了後
B32: ！ 追加要件 | C32: スコープ外の追加要件は別途お見積り
B33: ！ スケジュール | C33: 着手日確定後に詳細スケジュールを提示（「スケジュール」シート参照）
B34: ！ リソース | C34: S3前提：2〜3名チーム（FE×1 + BE/AI×1 + QA×0.5 + PM×0.5）
A36: 4. 前提と仮定（確定事項）
B37: 項目 | C37: 内容 | D37: ステータス
B38: AIプロバイダ | C38: OpenAI GPT-4o（推奨）、変更可 | D38: 確定後契約
B39: GT（模範文書） | C39: Skrum様より契約後30日以内にご提供 | D39: 必須
B40: AI精度目標 | C40: 文書生成90%以上・コンテンツ抽出95%以上 | D40: POC検証後確定
B41: 競合分析データ | C41: 手動入力＋公開情報の検索 | D41: 仕様確定時
B42: インボイス制度 | C42: 要対応（適格請求書番号項目実装） | D42: 基本設計反映
B43: 17画面仕様 | C43: 本見積対象外（別途見積） | D43: スコープ外
B44: ものづくり補助金 | C44: 本見積は補助金申請書類として使用可能 | D44: 対応済

Sheet 詳細見積
A1: 詳細見積書（WBSレベル）— AiBoシステム開発
A3: WBS ID | B3: カテゴリ | C3: 機能名 | D3: AI80% (MD) | E3: AI90% (MD) | F3: BE (MD) | G3: FE (MD) | H3: QA S1 (MD) | I3: QA S2 (MD) | J3: QA S3 (MD) | K3: QA S4 (MD) | L3: 備考
A4: AIBO-001 | B4: ダッシュボード | C4: ダッシュボード | D4: 0 | E4: 0 | F4: 1 | G4: 2 | H4: =50% * G4 -> 1 | I4: =50% * G4 + 40% * F4 -> 1.4 | J4: =50% * G4 + 40% * F4 + D4*60% -> 1.4 | K4: =50% * G4 + 40% * F4 + E4*60% -> 1.4
A5: AIBO-002 | B5: ファイル管理 | C5: ファイルアップロード | D5: 0 | E5: 0 | F5: 1 | G5: 1 | H5: =50% * G5 -> 0.5 | I5: =50% * G5 + 40% * F5 -> 0.9 | J5: =50% * G5 + 40% * F5 + D5*60% -> 0.9 | K5: =50% * G5 + 40% * F5 + E5*60% -> 0.9
A6: AIBO-003 | B6: AI文書生成 | C6: AIコンテンツ抽出 | D6: 8 | E6: 15 | F6: 4 | G6: 2 | H6: =50% * G6 -> 1 | I6: =50% * G6 + 40% * F6 -> 2.6 | J6: =50% * G6 + 40% * F6 + D6*60% -> 7.4 | K6: =50% * G6 + 40% * F6 + E6*60% -> 11.6 | L6: ⚠️ AI重要機能
A7: AIBO-004 | B7: ファイル管理 | C7: ファイル一覧・並替 | D7: 0 | E7: 0 | F7: 1 | G7: 3 | H7: =50% * G7 -> 1.5 | I7: =50% * G7 + 40% * F7 -> 1.9 | J7: =50% * G7 + 40% * F7 + D7*60% -> 1.9 | K7: =50% * G7 + 40% * F7 + E7*60% -> 1.9
A8: AIBO-005 | B8: ファイル管理 | C8: ファイル削除 | D8: 0 | E8: 0 | F8: 0.4 | G8: 0.4 | H8: =50% * G8 -> 0.2 | I8: =50% * G8 + 40% * F8 -> 0.36 | J8: =50% * G8 + 40% * F8 + D8*60% -> 0.36 | K8: =50% * G8 + 40% * F8 + E8*60% -> 0.36
A9: AIBO-006 | B9: ファイル管理 | C9: ファイルダウンロード | D9: 0 | E9: 0 | F9: 1 | G9: 1 | H9: =50% * G9 -> 0.5 | I9: =50% * G9 + 40% * F9 -> 0.9 | J9: =50% * G9 + 40% * F9 + D9*60% -> 0.9 | K9: =50% * G9 + 40% * F9 + E9*60% -> 0.9
A10: AIBO-007 | B10: AI文書生成 | C10: 提案書作成 | D10: 7 | E10: 12 | F10: 4 | G10: 2 | H10: =50% * G10 -> 1 | I10: =50% * G10 + 40% * F10 -> 2.6 | J10: =50% * G10 + 40% * F10 + D10*60% -> 6.8 | K10: =50% * G10 + 40% * F10 + E10*60% -> 9.8 | L10: ⚠️ AI重要機能
A11: AIBO-008 | B11: AI文書生成 | C11: 見積書作成 | D11: 3 | E11: 6 | F11: 2 | G11: 2 | H11: =50% * G11 -> 1 | I11: =50% * G11 + 40% * F11 -> 1.8 | J11: =50% * G11 + 40% * F11 + D11*60% -> 3.6 | K11: =50% * G11 + 40% * F11 + E11*60% -> 5.4 | L11: ⚠️ AI重要機能
A12: AIBO-009 | B12: AI文書生成 | C12: 請求書作成 | D12: 3 | E12: 6 | F12: 2 | G12: 2 | H12: =50% * G12 -> 1 | I12: =50% * G12 + 40% * F12 -> 1.8 | J12: =50% * G12 + 40% * F12 + D12*60% -> 3.6 | K12: =50% * G12 + 40% * F12 + E12*60% -> 5.4 | L12: ⚠️ AI重要機能
A13: AIBO-010 | B13: AI文書生成 | C13: 競合分析 | D13: 4 | E13: 7 | F13: 1 | G13: 2 | H13: =50% * G13 -> 1 | I13: =50% * G13 + 40% * F13 -> 1.4 | J13: =50% * G13 + 40% * F13 + D13*60% -> 3.8 | K13: =50% * G13 + 40% * F13 + E13*60% -> 5.6 | L13: ⚠️ AI重要機能
A14: AIBO-011 | B14: AI設定 | C14: AIテンプレート設定 | D14: 6 | E14: 10 | F14: 4 | G14: 4 | H14: =50% * G14 -> 2 | I14: =50% * G14 + 40% * F14 -> 3.6 | J14: =50% * G14 + 40% * F14 + D14*60% -> 7.2 | K14: =50% * G14 + 40% * F14 + E14*60% -> 9.6 | L14: ⚠️ AI重要機能
A15: AIBO-012 | B15: AI設定 | C15: マーケットプレイス | D15: 0 | E15: 0 | F15: 5 | G15: 5 | H15: =50% * G15 -> 2.5 | I15: =50% * G15 + 40% * F15 -> 4.5 | J15: =50% * G15 + 40% * F15 + D15*60% -> 4.5 | K15: =50% * G15 + 40% * F15 + E15*60% -> 4.5
A16: AIBO-013 | B16: 設定 | C16: ユーザ情報 | D16: 0 | E16: 0 | F16: 1 | G16: 2 | H16: =50% * G16 -> 1 | I16: =50% * G16 + 40% * F16 -> 1.4 | J16: =50% * G16 + 40% * F16 + D16*60% -> 1.4 | K16: =50% * G16 + 40% * F16 + E16*60% -> 1.4
A17: AIBO-014 | B17: 設定 | C17: 料金プラン | D17: 0 | E17: 0 | F17: 4 | G17: 4 | H17: =50% * G17 -> 2 | I17: =50% * G17 + 40% * F17 -> 3.6 | J17: =50% * G17 + 40% * F17 + D17*60% -> 3.6 | K17: =50% * G17 + 40% * F17 + E17*60% -> 3.6
A18: AIBO-015 | B18: 設定 | C18: 通知設定 | D18: 0 | E18: 0 | F18: 0.5 | G18: 1.5 | H18: =50% * G18 -> 0.75 | I18: =50% * G18 + 40% * F18 -> 0.95 | J18: =50% * G18 + 40% * F18 + D18*60% -> 0.95 | K18: =50% * G18 + 40% * F18 + E18*60% -> 0.95
A19: AIBO-016 | B19: 設定 | C19: パスワード変更 | D19: 0 | E19: 0 | F19: 0.4 | G19: 0.4 | H19: =50% * G19 -> 0.2 | I19: =50% * G19 + 40% * F19 -> 0.36 | J19: =50% * G19 + 40% * F19 + D19*60% -> 0.36 | K19: =50% * G19 + 40% * F19 + E19*60% -> 0.36
A20: AIBO-017 | B20: お問合せ | C20: お問合せフォーム | D20: 0 | E20: 0 | F20: 0.4 | G20: 0.4 | H20: =50% * G20 -> 0.2 | I20: =50% * G20 + 40% * F20 -> 0.36 | J20: =50% * G20 + 40% * F20 + D20*60% -> 0.36 | K20: =50% * G20 + 40% * F20 + E20*60% -> 0.36
A21: AIBO-018 | B21: 管理:認証 | C21: ログイン・ログアウト | D21: 0 | E21: 0 | F21: 0.6 | G21: 0.4 | H21: =50% * G21 -> 0.2 | I21: =50% * G21 + 40% * F21 -> 0.44 | J21: =50% * G21 + 40% * F21 + D21*60% -> 0.44 | K21: =50% * G21 + 40% * F21 + E21*60% -> 0.44
A22: AIBO-019 | B22: 管理:テナント | C22: テナント一覧・検索 | D22: 0 | E22: 0 | F22: 0.4 | G22: 0.6 | H22: =50% * G22 -> 0.3 | I22: =50% * G22 + 40% * F22 -> 0.46 | J22: =50% * G22 + 40% * F22 + D22*60% -> 0.46 | K22: =50% * G22 + 40% * F22 + E22*60% -> 0.46
A23: AIBO-020 | B23: 管理:テナント | C23: テナント作成 | D23: 0 | E23: 0 | F23: 2 | G23: 1 | H23: =50% * G23 -> 0.5 | I23: =50% * G23 + 40% * F23 -> 1.3 | J23: =50% * G23 + 40% * F23 + D23*60% -> 1.3 | K23: =50% * G23 + 40% * F23 + E23*60% -> 1.3
A24: AIBO-021 | B24: 管理:テナント | C24: テナント編集 | D24: 0 | E24: 0 | F24: 0.8 | G24: 0.7 | H24: =50% * G24 -> 0.35 | I24: =50% * G24 + 40% * F24 -> 0.67 | J24: =50% * G24 + 40% * F24 + D24*60% -> 0.67 | K24: =50% * G24 + 40% * F24 + E24*60% -> 0.67
A25: AIBO-022 | B25: 管理:テナント | C25: テナント停止・削除 | D25: 0 | E25: 0 | F25: 0.6 | G25: 0.4 | H25: =50% * G25 -> 0.2 | I25: =50% * G25 + 40% * F25 -> 0.44 | J25: =50% * G25 + 40% * F25 + D25*60% -> 0.44 | K25: =50% * G25 + 40% * F25 + E25*60% -> 0.44
A26: AIBO-023 | B26: 管理:プラン | C26: プラン一覧 | D26: 0 | E26: 0 | F26: 0.4 | G26: 0.4 | H26: =50% * G26 -> 0.2 | I26: =50% * G26 + 40% * F26 -> 0.36 | J26: =50% * G26 + 40% * F26 + D26*60% -> 0.36 | K26: =50% * G26 + 40% * F26 + E26*60% -> 0.36
A27: AIBO-024 | B27: 管理:プラン | C27: プラン編集 | D27: 0 | E27: 0 | F27: 0.6 | G27: 0.4 | H27: =50% * G27 -> 0.2 | I27: =50% * G27 + 40% * F27 -> 0.44 | J27: =50% * G27 + 40% * F27 + D27*60% -> 0.44 | K27: =50% * G27 + 40% * F27 + E27*60% -> 0.44

Sheet カテゴリ別集計
A1: カテゴリ別集計
A3: カテゴリ | B3: 機能数 | C3: AI (MD) | D3: BE (MD) | E3: FE (MD) | F3: QA (MD) | G3: 合計 (MD) | H3: 人月 | I3: 割合(%)
A4: ダッシュボード | B4: 1 | D4: 0.5 | E4: 1 | F4: 2 | G4: 3.5 | H4: 0.17 | I4: 100%
A5: ファイル管理 | B5: 4 | D5: 1.65 | E5: 2.6 | F5: 2 | G5: 6.25 | H5: 0.31 | I5: 64%
A6: AI文書生成 | B6: 5 | C6: 28.5 | D6: 6.5 | E6: 5 | F6: 20 | G6: 60 | H6: 3 | I6: 86%
A7: AI設定 | B7: 2 | D7: 0.65 | E7: 0.6 | F7: 0.6 | G7: 1.85 | H7: 0.09 | I7: 3%
A8: 設定 | B8: 4 | C8: 13 | D8: 4 | E8: 3 | F8: 9 | G8: 29 | H8: 1.45 | I8: 29%
A9: お問合せ | B9: 1 | C9: 3.5 | D9: 0.5 | E9: 1 | F9: 3 | G9: 8 | H9: 0.4 | I9: 7%
A10: 管理:認証 | B10: 1 | I10: 0%
A11: 管理:テナント | B11: =COUNTIF(詳細見積!$B$4:$B$40,"管理:テナント") -> 4 | C11: =SUMIF(詳細見積!$B$4:$B$40,"管理:テナント",詳細見積!$D$4:$D$40) -> 0 | D11: =SUMIF(詳細見積!$B$4:$B$40,"管理:テナント",詳細見積!$E$4:$E$40) -> 0 | E11: =SUMIF(詳細見積!$B$4:$B$40,"管理:テナント",詳細見積!$F$4:$F$40) -> 3.8 | F11: =SUMIF(詳細見積!$B$4:$B$40,"管理:テナント",詳細見積!$G$4:$G$40) -> 2.7 | G11: =C11+D11+E11+F11 -> 6.5 | H11: =G11/20 -> 0.325 | I11: =G11/G14 -> 0.05560308
A12: 管理:プラン | B12: =COUNTIF(詳細見積!$B$4:$B$40,"管理:プラン") -> 2 | C12: =SUMIF(詳細見積!$B$4:$B$40,"管理:プラン",詳細見積!$D$4:$D$40) -> 0 | D12: =SUMIF(詳細見積!$B$4:$B$40,"管理:プラン",詳細見積!$E$4:$E$40) -> 0 | E12: =SUMIF(詳細見積!$B$4:$B$40,"管理:プラン",詳細見積!$F$4:$F$40) -> 1 | F12: =SUMIF(詳細見積!$B$4:$B$40,"管理:プラン",詳細見積!$G$4:$G$40) -> 0.8 | G12: =C12+D12+E12+F12 -> 1.8 | H12: =G12/20 -> 0.09 | I12: =G12/G14 -> 0.015397776
A14: 合計 | B14: =SUM(B4:B12) -> 24 | C14: =SUM(C4:C12) -> 45 | D14: =SUM(D4:D12) -> 13.8 | E14: =SUM(E4:E12) -> 18 | F14: =SUM(F4:F12) -> 40.1 | G14: =SUM(G4:G12) -> 116.9 | H14: =G14/20 -> 5.845 | I14: 100.0%
A16: ※ AI文書生成・AI設定 の合計工数が全体の約60-70%を占める（AIパイプライン複雑度による）

Sheet 支払条件
A1: 支払条件 — AiBoシステム開発
A3: 【Skrum様】支払スケジュール
A4: 回 | B4: タイミング | C4: 支払割合 | D4: 金額（税別） | E4: 条件
A5: 1回目 | B5: 契約時 | C5: 30% | D5: ¥2,940,000 | E5: 契約締後5営業日以内
A6: 2回目 | B6: MS-04：全機能実装完了 | C6: 40% | D6: ¥3,920,000 | E6: コードFIX完了確認後5営業日以内
A7: 3回目 | B7: MS-07：受入テスト完了・納品 | C7: 30% | D7: ¥2,940,000 | E7: UAT完了・納品物引渡後5営業日以内
A9: 合計 | C9: 100% | D9: ¥9,800,000
A11: 【Skrum様】提供事項
A12: 項目 | B12: 内容 | C12: 期限
A13: GT（模範文書） | B13: 提案書・見積書・請求書 各5〜10件 | C13: 契約後30日以内
A14: Figmaデザイン | B14: 確定版画面デザイン | C14: 開発開始1週間前
A15: テストデータ | B15: 各機能のテスト用データ | C15: 結合試験開始時
A16: ※ ものづくり補助金申請用として本見積をご利用いただけます。 | B16: UAT実施環境（Web） | C16: UAT開始時
A18: ※ 支払は銀行振込。振込手数料はSkrum様負担。
A19: ※ ものづくり補助金申請用として本見積をご利用いただけます。

Sheet スケジュール
A1: プロジェクトスケジュール — S3シナリオ（推奨：9.8MM、約5ヶ月）
A2: プロジェクトスケジュール — Skrum様 AiBo (S3)
A3: フェーズ | B3: 開始 | C3: 終了 | D3: 期間 | E3: 備考
A4: 要件定義 | B4: M1 W1 | C4: M1 W3 | D4: 3週間 | E4: ヒアリング・スコープ確定・要件書作成
A5: 基本設計 | B5: M1 W3 | C5: M2 W2 | D5: 3週間 | E5: アーキテクチャ・画面設計・API設計
A6: 詳細設計 | B6: M2 W2 | C6: M3 W1 | D6: 3週間 | E6: DB設計・詳細仕様・インターフェース定義
A7: 製造（Sprint 1） | B7: M3 W1 | C7: M3 W3 | D7: 2週間 | E7: ダッシュボード・認証・ファイル管理基盤
A8: 製造（Sprint 2） | B8: M3 W3 | C8: M4 W2 | D8: 2週間 | E8: AI文書生成コア（提案書・見積書）
A9: 製造（Sprint 3） | B9: M4 W2 | C9: M5 W1 | D9: 3週間 | E9: 競合分析・AIテンプレート・マーケット
A10: 製造（Sprint 4） | B10: M5 W1 | C10: M5 W2 | D10: 1週間 | E10: 管理機能・設定・バグ修正
A11: 単体試験 | B11: M4 W1 | C11: M5 W3 | D11: 並行 | E11: 開発と並行実施（自動テスト + レビュー）
A12: 結合試験 | B12: M5 W3 | C12: M6 W2 | D12: 3週間 | E12: シナリオテスト・APIテスト・負荷テスト
A13: 受入テスト支援 | B13: M6 W2 | C13: M6 W4 | D13: 2週間 | E13: UAT支援・不具合対応・リリース準備
A15: 主要マイルストーン
A16: MS-01 | B16: M1 W4 | C16: 要件定義完了・スコープFIX
A17: MS-02 | B17: M2 W4 | C17: 基本設計完了・画面FIX
A18: MS-03 | B18: M3 W4 | C18: 詳細設計完了・DB FIX
A19: MS-04 | B19: M5 W2 | C19: 全機能実装完了（コードFIX）
A20: MS-05 | B20: M5 W4 | C20: 単体試験完了
A21: MS-06 | B21: M6 W3 | C21: 結合試験完了・本番候補リリース
A22: MS-07 | B22: M6 W4 | C22: 受入テスト完了・納品 | E22: ★最終マイルストーン
A24: ※ M = 着手月（プロジェクト開始月を M1 とする相対表記）。W = 週。
A25: ※ S3シナリオ前提：2〜3名チーム（FE×1 + BE/AI×1 + QA×0.5 + PM×0.5）
A26: ※ 製造フェーズはアジャイル（2週スプリント）で進行。スプリントごとにデモを実施。
A27: ※ 着手日確定後、Mを実際の暦日付に変換した詳細ガントチャートを提出可能。
A28: ※ チーム構成：平均1.7名（FE×0.6 + BE/AI×0.8 + QA×0.3 + PM×0.5）
A29: ※ ピーク時：製造フェーズで最大2.5名（FE×1 + BE/AI×1 + QA×0.5）
A30: 【POC期間】基本設計完了後2週間
A31: 目的：AI精度検証、LLM選定確認
A32: 成果：精度レポート、最終LLM決定
